[
  {
    "id": "38d6831b899f245c",
    "source_id": "berlin-events",
    "source": "Berlin.de Veranstaltungskalender",
    "source_url": "https://www.berlin.de/land/kalender/index.php?detail=284047&ls=0&c=13&date_start=06.07.2026",
    "title": "Lesung mit Dietmar Arnold und Helmut Müller-Enbergs - 07.07.2026 Operation Gold. Der Spionagetunnel in Berlin",
    "published_at": "2026-07-07T18:30:00.000Z",
    "ingested_at": "2026-07-06T08:24:57.966Z",
    "raw_excerpt": "Ort: Stadtteilbibliothek Altglienicke in Treptow-Köpenick",
    "ai_summary": "Veranstaltung am 7. Juli um 18:30 in Stadtteilbibliothek Altglienicke in Treptow-Köpenick.",
    "tags": [
      "veranstaltung"
    ],
    "location": "Köpenick",
    "location_relevant": true,
    "local_relevance_score": 0.75,
    "political_relevance_score": 0.1,
    "election_relevant": false,
    "ai_reasoning": "Veranstaltung im Bezirk Treptow-Köpenick.",
    "event_start_at": "2026-07-07T18:30:00.000Z",
    "venue": "Stadtteilbibliothek Altglienicke in Treptow-Köpenick",
    "district": "Altglienicke",
    "addresses": [],
    "lat": 52.4450491,
    "lng": 13.5754153,
    "is_mock": false
  },
  {
    "id": "94e28ef37d1ce3cc",
    "source_id": "bezirksamt-tk",
    "source": "Bezirksamt Treptow-Köpenick",
    "source_url": "https://www.berlin.de/ba-treptow-koepenick/aktuelles/pressemitteilungen/2026/pressemitteilung.1690322.php",
    "title": "Baumfällungen in der Woche vom 6. bis 10. Juli 2026",
    "published_at": "2026-07-06T12:00:00.000Z",
    "ingested_at": "2026-07-07T07:42:28.486Z",
    "raw_excerpt": "",
    "ai_summary": "Offizielle Meldung des Bezirksamts Treptow-Köpenick. Details stehen in der Originalquelle.",
    "tags": [
      "verwaltung",
      "infrastruktur"
    ],
    "location": "Treptow-Köpenick",
    "location_relevant": true,
    "local_relevance_score": 0.7,
    "political_relevance_score": 0.3,
    "election_relevant": false,
    "ai_reasoning": "Offizielle Pressemitteilung des Bezirksamts Treptow-Köpenick.",
    "district": "Treptow",
    "addresses": [],
    "is_mock": false
  },
  {
    "id": "28a1ad5db81bca86",
    "source_id": "bezirksamt-tk",
    "source": "Bezirksamt Treptow-Köpenick",
    "source_url": "https://www.berlin.de/ba-treptow-koepenick/aktuelles/pressemitteilungen/2026/pressemitteilung.1690128.php",
    "title": "Größte Neubauschule Berlins fertiggestellt: HOWOGE übergibt Gemeinschaftsschule an Bezirk Treptow-Köpenick",
    "published_at": "2026-07-06T12:00:00.000Z",
    "ingested_at": "2026-07-07T07:42:28.486Z",
    "raw_excerpt": "",
    "ai_summary": "Offizielle Meldung des Bezirksamts Treptow-Köpenick. Details stehen in der Originalquelle.",
    "tags": [
      "verwaltung",
      "infrastruktur"
    ],
    "location": "Köpenick",
    "location_relevant": true,
    "local_relevance_score": 0.7,
    "political_relevance_score": 0.3,
    "election_relevant": false,
    "ai_reasoning": "Offizielle Pressemitteilung des Bezirksamts Treptow-Köpenick.",
    "district": "Treptow",
    "addresses": [],
    "lat": 52.4450491,
    "lng": 13.5754153,
    "is_mock": false
  },
  {
    "id": "3000251a085d44c7",
    "source_id": "berlin-events",
    "source": "Berlin.de Veranstaltungskalender",
    "source_url": "https://www.berlin.de/land/kalender/index.php?detail=284032&ls=0&c=13&date_start=05.07.2026",
    "title": "Sturzprophylaxe: – Sicher und aktiv im Alter",
    "published_at": "2026-07-06T10:15:00.000Z",
    "ingested_at": "2026-07-05T07:30:18.067Z",
    "raw_excerpt": "Ort: KES - Generationsklub in Oberschöneweide in Treptow-Köpenick",
    "ai_summary": "Veranstaltung am 6. Juli um 10:15 in KES - Generationsklub in Oberschöneweide in Treptow-Köpenick.",
    "tags": [
      "veranstaltung"
    ],
    "location": "Köpenick",
    "location_relevant": true,
    "local_relevance_score": 0.75,
    "political_relevance_score": 0.1,
    "election_relevant": false,
    "ai_reasoning": "Veranstaltung im Bezirk Treptow-Köpenick.",
    "event_start_at": "2026-07-06T10:15:00.000Z",
    "venue": "KES - Generationsklub in Oberschöneweide in Treptow-Köpenick",
    "district": "Oberschöneweide",
    "addresses": [],
    "lat": 52.4450491,
    "lng": 13.5754153,
    "is_mock": false
  },
  {
    "id": "1dc56a8ff25e6504",
    "source_id": "berlin-events",
    "source": "Berlin.de Veranstaltungskalender",
    "source_url": "https://www.berlin.de/land/kalender/index.php?detail=275236&ls=0&c=13&date_start=05.07.2026",
    "title": "NS-Zwangsarbeit im Film - International Summer School",
    "published_at": "2026-07-05T12:00:00.000Z",
    "ingested_at": "2026-07-05T07:30:18.064Z",
    "raw_excerpt": "Ort: Dokumentationszentrum NS-Zwangsarbeit in Treptow-Köpenick",
    "ai_summary": "Veranstaltung am 5. Juli um 12:00 in Dokumentationszentrum NS-Zwangsarbeit in Treptow-Köpenick.",
    "tags": [
      "veranstaltung"
    ],
    "location": "Köpenick",
    "location_relevant": true,
    "local_relevance_score": 0.75,
    "political_relevance_score": 0.1,
    "election_relevant": false,
    "ai_reasoning": "Veranstaltung im Bezirk Treptow-Köpenick.",
    "event_start_at": "2026-07-05T12:00:00.000Z",
    "venue": "Dokumentationszentrum NS-Zwangsarbeit in Treptow-Köpenick",
    "district": "Treptow",
    "addresses": [],
    "lat": 52.4450491,
    "lng": 13.5754153,
    "is_mock": false
  },
  {
    "id": "34f839fa1aedca13",
    "source_id": "berlin-events",
    "source": "Berlin.de Veranstaltungskalender",
    "source_url": "https://www.berlin.de/land/kalender/index.php?detail=284566&ls=0&c=13&date_start=04.07.2026",
    "title": "Drittes Coloniafest in Altglienicke",
    "published_at": "2026-07-04T14:00:00.000Z",
    "ingested_at": "2026-07-04T06:49:24.429Z",
    "raw_excerpt": "Ort: Coloniapark in Treptow-Köpenick",
    "ai_summary": "Veranstaltung am 4. Juli um 14:00 in Coloniapark in Treptow-Köpenick.",
    "tags": [
      "veranstaltung"
    ],
    "location": "Köpenick",
    "location_relevant": true,
    "local_relevance_score": 0.75,
    "political_relevance_score": 0.1,
    "election_relevant": false,
    "ai_reasoning": "Veranstaltung im Bezirk Treptow-Köpenick.",
    "event_start_at": "2026-07-04T14:00:00.000Z",
    "venue": "Coloniapark in Treptow-Köpenick",
    "district": "Altglienicke",
    "addresses": [],
    "lat": 52.4450491,
    "lng": 13.5754153,
    "is_mock": false
  },
  {
    "id": "4dc770bb842581bb",
    "source_id": "berlin-events",
    "source": "Berlin.de Veranstaltungskalender",
    "source_url": "https://www.berlin.de/land/kalender/index.php?detail=284086&ls=0&c=13&date_start=04.07.2026",
    "title": "Familiensamstag",
    "published_at": "2026-07-04T11:00:00.000Z",
    "ingested_at": "2026-07-04T06:49:24.429Z",
    "raw_excerpt": "Ort: Mittelpunktbibliothek Treptow in Treptow-Köpenick",
    "ai_summary": "Veranstaltung am 4. Juli um 11:00 in Mittelpunktbibliothek Treptow in Treptow-Köpenick.",
    "tags": [
      "veranstaltung"
    ],
    "location": "Köpenick",
    "location_relevant": true,
    "local_relevance_score": 0.75,
    "political_relevance_score": 0.1,
    "election_relevant": false,
    "ai_reasoning": "Veranstaltung im Bezirk Treptow-Köpenick.",
    "event_start_at": "2026-07-04T11:00:00.000Z",
    "venue": "Mittelpunktbibliothek Treptow in Treptow-Köpenick",
    "district": "Treptow",
    "addresses": [],
    "lat": 52.4450491,
    "lng": 13.5754153,
    "is_mock": false
  },
  {
    "id": "c52a552f2d073238",
    "source_id": "berlin-events",
    "source": "Berlin.de Veranstaltungskalender",
    "source_url": "https://www.berlin.de/land/kalender/index.php?detail=284029&ls=0&c=13&date_start=03.07.2026",
    "title": "Backwerkstatt",
    "published_at": "2026-07-04T10:00:00.000Z",
    "ingested_at": "2026-07-03T07:24:25.443Z",
    "raw_excerpt": "Ort: Kiezclub Alte Schule Adlershof in Treptow-Köpenick",
    "ai_summary": "Veranstaltung am 4. Juli um 10:00 in Kiezclub Alte Schule Adlershof in Treptow-Köpenick.",
    "tags": [
      "veranstaltung"
    ],
    "location": "Köpenick",
    "location_relevant": true,
    "local_relevance_score": 0.75,
    "political_relevance_score": 0.1,
    "election_relevant": false,
    "ai_reasoning": "Veranstaltung im Bezirk Treptow-Köpenick.",
    "event_start_at": "2026-07-04T10:00:00.000Z",
    "venue": "Kiezclub Alte Schule Adlershof in Treptow-Köpenick",
    "district": "Adlershof",
    "addresses": [],
    "lat": 52.4450491,
    "lng": 13.5754153,
    "is_mock": false
  },
  {
    "id": "c8a41b34ce90eaca",
    "source_id": "berlin-events",
    "source": "Berlin.de Veranstaltungskalender",
    "source_url": "https://www.berlin.de/land/kalender/index.php?detail=284026&ls=0&c=13&date_start=03.07.2026",
    "title": "KLUBFrühstück & Poesie",
    "published_at": "2026-07-04T10:00:00.000Z",
    "ingested_at": "2026-07-03T07:24:25.443Z",
    "raw_excerpt": "Ort: Kiezklub Allende-Viertel in Treptow-Köpenick",
    "ai_summary": "Veranstaltung am 4. Juli um 10:00 in Kiezklub Allende-Viertel in Treptow-Köpenick.",
    "tags": [
      "veranstaltung"
    ],
    "location": "Köpenick",
    "location_relevant": true,
    "local_relevance_score": 0.75,
    "political_relevance_score": 0.1,
    "election_relevant": false,
    "ai_reasoning": "Veranstaltung im Bezirk Treptow-Köpenick.",
    "event_start_at": "2026-07-04T10:00:00.000Z",
    "venue": "Kiezklub Allende-Viertel in Treptow-Köpenick",
    "district": "Treptow",
    "addresses": [],
    "lat": 52.4450491,
    "lng": 13.5754153,
    "is_mock": false
  },
  {
    "id": "47b75d853177d9fb",
    "source_id": "berlin-events",
    "source": "Berlin.de Veranstaltungskalender",
    "source_url": "https://www.berlin.de/land/kalender/index.php?detail=284023&ls=0&c=13&date_start=03.07.2026",
    "title": "Frühstück für alle Generationen",
    "published_at": "2026-07-04T10:00:00.000Z",
    "ingested_at": "2026-07-03T07:24:25.444Z",
    "raw_excerpt": "Ort: Kiezklub Allende-Viertel in Treptow-Köpenick",
    "ai_summary": "Veranstaltung am 4. Juli um 10:00 in Kiezklub Allende-Viertel in Treptow-Köpenick.",
    "tags": [
      "veranstaltung"
    ],
    "location": "Köpenick",
    "location_relevant": true,
    "local_relevance_score": 0.75,
    "political_relevance_score": 0.1,
    "election_relevant": false,
    "ai_reasoning": "Veranstaltung im Bezirk Treptow-Köpenick.",
    "event_start_at": "2026-07-04T10:00:00.000Z",
    "venue": "Kiezklub Allende-Viertel in Treptow-Köpenick",
    "district": "Treptow",
    "addresses": [],
    "lat": 52.4450491,
    "lng": 13.5754153,
    "is_mock": false
  },
  {
    "id": "ab73943cdb4e8ae1",
    "source_id": "bezirksamt-tk",
    "source": "Bezirksamt Treptow-Köpenick",
    "source_url": "https://www.berlin.de/ba-treptow-koepenick/aktuelles/pressemitteilungen/2026/pressemitteilung.1688542.php",
    "title": "„AKTIV IN TREPTOW-KÖPENICK“: Erfolgreiche Informationsveranstaltung begleitet den Übergang in den Ruhestand",
    "published_at": "2026-07-03T12:00:00.000Z",
    "ingested_at": "2026-07-03T07:24:25.446Z",
    "raw_excerpt": "",
    "ai_summary": "Offizielle Meldung des Bezirksamts Treptow-Köpenick. Details stehen in der Originalquelle.",
    "tags": [
      "verwaltung"
    ],
    "location": "Köpenick",
    "location_relevant": true,
    "local_relevance_score": 0.7,
    "political_relevance_score": 0.3,
    "election_relevant": false,
    "ai_reasoning": "Offizielle Pressemitteilung des Bezirksamts Treptow-Köpenick.",
    "district": "Treptow",
    "addresses": [],
    "lat": 52.4450491,
    "lng": 13.5754153,
    "is_mock": false
  },
  {
    "id": "0892d923e75a5337",
    "source_id": "berlin-events",
    "source": "Berlin.de Veranstaltungskalender",
    "source_url": "https://www.berlin.de/land/kalender/index.php?detail=284071&ls=0&c=13&date_start=02.07.2026",
    "title": "Buchvorstellung mit Wolfgang Bogumil",
    "published_at": "2026-07-02T18:30:00.000Z",
    "ingested_at": "2026-07-02T07:35:34.491Z",
    "raw_excerpt": "Ort: Stadtteilbibliothek Altglienicke in Treptow-Köpenick",
    "ai_summary": "Veranstaltung am 2. Juli um 18:30 in Stadtteilbibliothek Altglienicke in Treptow-Köpenick.",
    "tags": [
      "veranstaltung"
    ],
    "location": "Köpenick",
    "location_relevant": true,
    "local_relevance_score": 0.75,
    "political_relevance_score": 0.1,
    "election_relevant": false,
    "ai_reasoning": "Veranstaltung im Bezirk Treptow-Köpenick.",
    "event_start_at": "2026-07-02T18:30:00.000Z",
    "venue": "Stadtteilbibliothek Altglienicke in Treptow-Köpenick",
    "district": "Altglienicke",
    "addresses": [],
    "lat": 52.4450491,
    "lng": 13.5754153,
    "is_mock": false
  },
  {
    "id": "478c563a909475f2",
    "source_id": "berlin-events",
    "source": "Berlin.de Veranstaltungskalender",
    "source_url": "https://www.berlin.de/land/kalender/index.php?detail=284020&ls=0&c=13&date_start=02.07.2026",
    "title": "Kaffeetafel",
    "published_at": "2026-07-02T14:30:00.000Z",
    "ingested_at": "2026-07-02T07:35:34.491Z",
    "raw_excerpt": "Ort: KIEZKLUB Gerard Philipe in Treptow-Köpenick",
    "ai_summary": "Veranstaltung am 2. Juli um 14:30 in KIEZKLUB Gerard Philipe in Treptow-Köpenick.",
    "tags": [
      "veranstaltung"
    ],
    "location": "Köpenick",
    "location_relevant": true,
    "local_relevance_score": 0.75,
    "political_relevance_score": 0.1,
    "election_relevant": false,
    "ai_reasoning": "Veranstaltung im Bezirk Treptow-Köpenick.",
    "event_start_at": "2026-07-02T14:30:00.000Z",
    "venue": "KIEZKLUB Gerard Philipe in Treptow-Köpenick",
    "district": "Treptow",
    "addresses": [],
    "lat": 52.4450491,
    "lng": 13.5754153,
    "is_mock": false
  },
  {
    "id": "a7a84d1f9609c94c",
    "source_id": "berlin-events",
    "source": "Berlin.de Veranstaltungskalender",
    "source_url": "https://www.berlin.de/land/kalender/index.php?detail=284014&ls=0&c=13&date_start=02.07.2026",
    "title": "Tanzfest im Rathaushof",
    "published_at": "2026-07-02T14:00:00.000Z",
    "ingested_at": "2026-07-02T07:35:34.490Z",
    "raw_excerpt": "Ort: KIEZKLUB Rathaus Johannisthal in Treptow-Köpenick",
    "ai_summary": "Veranstaltung am 2. Juli um 14:00 in KIEZKLUB Rathaus Johannisthal in Treptow-Köpenick.",
    "tags": [
      "veranstaltung"
    ],
    "location": "Köpenick",
    "location_relevant": true,
    "local_relevance_score": 0.75,
    "political_relevance_score": 0.1,
    "election_relevant": false,
    "ai_reasoning": "Veranstaltung im Bezirk Treptow-Köpenick.",
    "event_start_at": "2026-07-02T14:00:00.000Z",
    "venue": "KIEZKLUB Rathaus Johannisthal in Treptow-Köpenick",
    "district": "Johannisthal",
    "addresses": [],
    "lat": 52.4450491,
    "lng": 13.5754153,
    "is_mock": false
  },
  {
    "id": "328bde93e9051cf7",
    "source_id": "berlin-events",
    "source": "Berlin.de Veranstaltungskalender",
    "source_url": "https://www.berlin.de/land/kalender/index.php?detail=284017&ls=0&c=13&date_start=02.07.2026",
    "title": "Mensch-ärgere-dich-nicht-Turnier",
    "published_at": "2026-07-02T14:00:00.000Z",
    "ingested_at": "2026-07-02T07:35:34.491Z",
    "raw_excerpt": "Ort: KIEZKLUB Vital in Treptow-Köpenick",
    "ai_summary": "Veranstaltung am 2. Juli um 14:00 in KIEZKLUB Vital in Treptow-Köpenick.",
    "tags": [
      "veranstaltung"
    ],
    "location": "Köpenick",
    "location_relevant": true,
    "local_relevance_score": 0.75,
    "political_relevance_score": 0.1,
    "election_relevant": false,
    "ai_reasoning": "Veranstaltung im Bezirk Treptow-Köpenick.",
    "event_start_at": "2026-07-02T14:00:00.000Z",
    "venue": "KIEZKLUB Vital in Treptow-Köpenick",
    "district": "Treptow",
    "addresses": [],
    "lat": 52.4450491,
    "lng": 13.5754153,
    "is_mock": false
  },
  {
    "id": "f9e591fe90ac91ac",
    "source_id": "berlin-events",
    "source": "Berlin.de Veranstaltungskalender",
    "source_url": "https://www.berlin.de/land/kalender/index.php?detail=284068&ls=0&c=13&date_start=02.07.2026",
    "title": "Zeitzeugengespräch mit Sonja Mühlberger - 02.07.2026 „Geboren in Shanghai als Kind von Emigranten. Leben und Überleben im Ghetto von Hongkew (1939-1947)“",
    "published_at": "2026-07-02T13:00:00.000Z",
    "ingested_at": "2026-07-02T07:35:34.490Z",
    "raw_excerpt": "Ort: Stadtteilbibliothek Altglienicke in Treptow-Köpenick",
    "ai_summary": "Veranstaltung am 2. Juli um 13:00 in Stadtteilbibliothek Altglienicke in Treptow-Köpenick.",
    "tags": [
      "veranstaltung"
    ],
    "location": "Köpenick",
    "location_relevant": true,
    "local_relevance_score": 0.75,
    "political_relevance_score": 0.1,
    "election_relevant": false,
    "ai_reasoning": "Veranstaltung im Bezirk Treptow-Köpenick.",
    "event_start_at": "2026-07-02T13:00:00.000Z",
    "venue": "Stadtteilbibliothek Altglienicke in Treptow-Köpenick",
    "district": "Altglienicke",
    "addresses": [],
    "lat": 52.4450491,
    "lng": 13.5754153,
    "is_mock": false
  },
  {
    "id": "d21f1eba78b9e8db",
    "source_id": "bezirksamt-tk",
    "source": "Bezirksamt Treptow-Köpenick",
    "source_url": "https://www.berlin.de/ba-treptow-koepenick/aktuelles/pressemitteilungen/2026/pressemitteilung.1688530.php",
    "title": "Night-Walk – Schöneweide am 4. Juli 2026. Sicherheit im öffentlichen Raum?",
    "published_at": "2026-07-02T12:00:00.000Z",
    "ingested_at": "2026-07-02T07:35:34.492Z",
    "raw_excerpt": "",
    "ai_summary": "Offizielle Meldung des Bezirksamts Treptow-Köpenick. Details stehen in der Originalquelle.",
    "tags": [
      "verwaltung"
    ],
    "location": "Treptow-Köpenick",
    "location_relevant": true,
    "local_relevance_score": 0.7,
    "political_relevance_score": 0.3,
    "election_relevant": false,
    "ai_reasoning": "Offizielle Pressemitteilung des Bezirksamts Treptow-Köpenick.",
    "district": "Treptow",
    "addresses": [],
    "is_mock": false
  },
  {
    "id": "36294fe8450481e1",
    "source_id": "bezirksamt-tk",
    "source": "Bezirksamt Treptow-Köpenick",
    "source_url": "https://www.berlin.de/ba-treptow-koepenick/aktuelles/pressemitteilungen/2026/pressemitteilung.1688826.php",
    "title": "Ein „Grüner Anger“ für den Plänterwald: Informationsveranstaltung zur Qualifizierung der Grünanlage Galileistraße/ Orionstraße",
    "published_at": "2026-07-02T12:00:00.000Z",
    "ingested_at": "2026-07-03T07:24:25.446Z",
    "raw_excerpt": "",
    "ai_summary": "Offizielle Meldung des Bezirksamts Treptow-Köpenick. Details stehen in der Originalquelle.",
    "tags": [
      "verwaltung",
      "verkehr"
    ],
    "location": "Treptow-Köpenick",
    "location_relevant": true,
    "local_relevance_score": 0.7,
    "political_relevance_score": 0.3,
    "election_relevant": false,
    "ai_reasoning": "Offizielle Pressemitteilung des Bezirksamts Treptow-Köpenick.",
    "district": "Treptow",
    "addresses": [],
    "is_mock": false
  },
  {
    "id": "d73b3fc35b527e10",
    "source_id": "bezirksamt-tk",
    "source": "Bezirksamt Treptow-Köpenick",
    "source_url": "https://www.berlin.de/ba-treptow-koepenick/aktuelles/pressemitteilungen/2026/pressemitteilung.1688781.php",
    "title": "Sprechstunde des Bezirksstadtrates Bernd Geschanowski am 6. Juli entfällt",
    "published_at": "2026-07-02T12:00:00.000Z",
    "ingested_at": "2026-07-03T07:24:25.446Z",
    "raw_excerpt": "",
    "ai_summary": "Offizielle Meldung des Bezirksamts Treptow-Köpenick. Details stehen in der Originalquelle.",
    "tags": [
      "verwaltung"
    ],
    "location": "Treptow-Köpenick",
    "location_relevant": true,
    "local_relevance_score": 0.7,
    "political_relevance_score": 0.3,
    "election_relevant": false,
    "ai_reasoning": "Offizielle Pressemitteilung des Bezirksamts Treptow-Köpenick.",
    "district": "Treptow",
    "addresses": [],
    "is_mock": false
  },
  {
    "id": "b3f0d89feca10eca",
    "source_id": "berlin-events",
    "source": "Berlin.de Veranstaltungskalender",
    "source_url": "https://www.berlin.de/land/kalender/index.php?detail=283906&ls=0&c=13&date_start=01.07.2026",
    "title": "Hebräischer Chor",
    "published_at": "2026-07-01T20:30:00.000Z",
    "ingested_at": "2026-07-01T08:16:08.830Z",
    "raw_excerpt": "Ort: KIEZKLUB Alte Schule in Treptow-Köpenick",
    "ai_summary": "Veranstaltung am 1. Juli um 20:30 in KIEZKLUB Alte Schule in Treptow-Köpenick.",
    "tags": [
      "veranstaltung"
    ],
    "location": "Köpenick",
    "location_relevant": true,
    "local_relevance_score": 0.75,
    "political_relevance_score": 0.1,
    "election_relevant": false,
    "ai_reasoning": "Veranstaltung im Bezirk Treptow-Köpenick.",
    "event_start_at": "2026-07-01T20:30:00.000Z",
    "venue": "KIEZKLUB Alte Schule in Treptow-Köpenick",
    "district": "Treptow",
    "addresses": [],
    "lat": 52.4450491,
    "lng": 13.5754153,
    "is_mock": false
  },
  {
    "id": "bd9fd4ad4bf0c311",
    "source_id": "berlin-events",
    "source": "Berlin.de Veranstaltungskalender",
    "source_url": "https://www.berlin.de/land/kalender/index.php?detail=284059&ls=0&c=13&date_start=01.07.2026",
    "title": "Rundgang am Dorfanger Bohnsdorf",
    "published_at": "2026-07-01T18:00:00.000Z",
    "ingested_at": "2026-07-01T08:16:08.830Z",
    "raw_excerpt": "Ort: Dorfplatz in Treptow-Köpenick",
    "ai_summary": "Veranstaltung am 1. Juli um 18:00 in Dorfplatz in Treptow-Köpenick.",
    "tags": [
      "veranstaltung"
    ],
    "location": "Köpenick",
    "location_relevant": true,
    "local_relevance_score": 0.75,
    "political_relevance_score": 0.1,
    "election_relevant": false,
    "ai_reasoning": "Veranstaltung im Bezirk Treptow-Köpenick.",
    "event_start_at": "2026-07-01T18:00:00.000Z",
    "venue": "Dorfplatz in Treptow-Köpenick",
    "district": "Bohnsdorf",
    "addresses": [],
    "lat": 52.4450491,
    "lng": 13.5754153,
    "is_mock": false
  },
  {
    "id": "49b6638de8da1cba",
    "source_id": "bezirksamt-tk",
    "source": "Bezirksamt Treptow-Köpenick",
    "source_url": "https://www.berlin.de/ba-treptow-koepenick/aktuelles/pressemitteilungen/2026/pressemitteilung.1688415.php",
    "title": "Runder Tisch Müll in Treptow-Köpenick: Akteure vernetzen sich für mehr Sauberkeit im Bezirk",
    "published_at": "2026-07-01T12:00:00.000Z",
    "ingested_at": "2026-07-02T07:35:34.493Z",
    "raw_excerpt": "",
    "ai_summary": "Offizielle Meldung des Bezirksamts Treptow-Köpenick. Details stehen in der Originalquelle.",
    "tags": [
      "verwaltung"
    ],
    "location": "Köpenick",
    "location_relevant": true,
    "local_relevance_score": 0.7,
    "political_relevance_score": 0.3,
    "election_relevant": false,
    "ai_reasoning": "Offizielle Pressemitteilung des Bezirksamts Treptow-Köpenick.",
    "district": "Treptow",
    "addresses": [],
    "lat": 52.4450491,
    "lng": 13.5754153,
    "is_mock": false
  },
  {
    "id": "583758e8db8a0276",
    "source_id": "bezirksamt-tk",
    "source": "Bezirksamt Treptow-Köpenick",
    "source_url": "https://www.berlin.de/ba-treptow-koepenick/aktuelles/pressemitteilungen/2026/pressemitteilung.1688351.php",
    "title": "STADTRADELN 2026 in Treptow-Köpenick: Die Bezirksteams radeln sich an die Spitze",
    "published_at": "2026-07-01T12:00:00.000Z",
    "ingested_at": "2026-07-02T07:35:34.493Z",
    "raw_excerpt": "",
    "ai_summary": "Offizielle Meldung des Bezirksamts Treptow-Köpenick. Details stehen in der Originalquelle.",
    "tags": [
      "verwaltung",
      "verkehr"
    ],
    "location": "Köpenick",
    "location_relevant": true,
    "local_relevance_score": 0.7,
    "political_relevance_score": 0.3,
    "election_relevant": false,
    "ai_reasoning": "Offizielle Pressemitteilung des Bezirksamts Treptow-Köpenick.",
    "district": "Treptow",
    "addresses": [],
    "lat": 52.4450491,
    "lng": 13.5754153,
    "is_mock": false
  },
  {
    "id": "80895a74951face5",
    "source_id": "bezirksamt-tk",
    "source": "Bezirksamt Treptow-Köpenick",
    "source_url": "https://www.berlin.de/ba-treptow-koepenick/aktuelles/pressemitteilungen/2026/pressemitteilung.1688312.php",
    "title": "BSR-Kieztag am 10. Juli in Rahnsdorf",
    "published_at": "2026-07-01T12:00:00.000Z",
    "ingested_at": "2026-07-02T07:35:34.493Z",
    "raw_excerpt": "",
    "ai_summary": "Offizielle Meldung des Bezirksamts Treptow-Köpenick. Details stehen in der Originalquelle.",
    "tags": [
      "verwaltung"
    ],
    "location": "Treptow-Köpenick",
    "location_relevant": true,
    "local_relevance_score": 0.7,
    "political_relevance_score": 0.3,
    "election_relevant": false,
    "ai_reasoning": "Offizielle Pressemitteilung des Bezirksamts Treptow-Köpenick.",
    "district": "Rahnsdorf",
    "addresses": [],
    "is_mock": false
  },
  {
    "id": "4b86f0a22ee8c065",
    "source_id": "bezirksamt-tk",
    "source": "Bezirksamt Treptow-Köpenick",
    "source_url": "https://www.berlin.de/ba-treptow-koepenick/aktuelles/pressemitteilungen/2026/pressemitteilung.1688283.php",
    "title": "LZ Dörpfeldstraße –Arbeiten in der Radickestraße schreiten voran",
    "published_at": "2026-07-01T12:00:00.000Z",
    "ingested_at": "2026-07-02T07:35:34.493Z",
    "raw_excerpt": "",
    "ai_summary": "Offizielle Meldung des Bezirksamts Treptow-Köpenick. Details stehen in der Originalquelle.",
    "tags": [
      "verwaltung",
      "verkehr"
    ],
    "location": "Treptow-Köpenick",
    "location_relevant": true,
    "local_relevance_score": 0.7,
    "political_relevance_score": 0.3,
    "election_relevant": false,
    "ai_reasoning": "Offizielle Pressemitteilung des Bezirksamts Treptow-Köpenick.",
    "district": "Treptow",
    "addresses": [],
    "is_mock": false
  },
  {
    "id": "da5395544f30066f",
    "source_id": "bezirksamt-tk",
    "source": "Bezirksamt Treptow-Köpenick",
    "source_url": "https://www.berlin.de/ba-treptow-koepenick/aktuelles/pressemitteilungen/2026/pressemitteilung.1688275.php",
    "title": "Ihre Erfahrungen zählen: Befragung zu Stromausfällen und Krisenkommunikation im Bezirk startet",
    "published_at": "2026-07-01T12:00:00.000Z",
    "ingested_at": "2026-07-02T07:35:34.493Z",
    "raw_excerpt": "",
    "ai_summary": "Offizielle Meldung des Bezirksamts Treptow-Köpenick. Details stehen in der Originalquelle.",
    "tags": [
      "verwaltung",
      "infrastruktur"
    ],
    "location": "Treptow-Köpenick",
    "location_relevant": true,
    "local_relevance_score": 0.7,
    "political_relevance_score": 0.3,
    "election_relevant": false,
    "ai_reasoning": "Offizielle Pressemitteilung des Bezirksamts Treptow-Köpenick.",
    "district": "Treptow",
    "addresses": [],
    "is_mock": false
  }
]
